apicultur/apicultur.py
apicultur/service.py
apicultur/test.py
apicultur/throttle.py
apicultur/utils.py
apicultur/__init__.py
apicultur/apicultur_io/aleatorias.py
apicultur/apicultur_io/english_to_phone.py
apicultur/apicultur_io/freeling_ner_es.py
apicultur/apicultur_io/freeling_numerical_es.py
apicultur/apicultur_io/freeling_parser_es.py
apicultur/apicultur_io/freeling_pos_tagger.py
apicultur/apicultur_io/freeling_semantic_tagger_es.py
apicultur/apicultur_io/freeling_sentence_splitter.py
apicultur/apicultur_io/freeling_syntax_analysis.py
apicultur/apicultur_io/freeling_tokenizer.py
apicultur/apicultur_io/phone_to_english.py
apicultur/apicultur_io/transitive_verb.py
apicultur/apicultur_io/__init__.py
apicultur/examples/cervantes_level.py
apicultur/examples/count_lemmas.py
apicultur/examples/count_NCC.py
apicultur/examples/count_verbos.py
apicultur/examples/__init__.py
apicultur/services/base.py
apicultur/services/calculador_frecuencia.py
apicultur/services/lematizador2.py
apicultur/services/nivel_cervantes.py
apicultur/services/__init__.py
apicultur/store_apicultur_com/acentuador.py
apicultur/store_apicultur_com/calculador_frecuencia.py
apicultur/store_apicultur_com/definicion_uno.py
apicultur/store_apicultur_com/etiquetador_morfologico.py
apicultur/store_apicultur_com/lematizador2.py
apicultur/store_apicultur_com/nivel_cervantes.py
apicultur/store_apicultur_com/segmenta_textos.py
apicultur/store_apicultur_com/silabeador_ortografico.py
apicultur/store_apicultur_com/__init__.py
apicultur-0.1.20.dist-info/DESCRIPTION.rst
apicultur-0.1.20.dist-info/METADATA
apicultur-0.1.20.dist-info/metadata.json
apicultur-0.1.20.dist-info/RECORD
apicultur-0.1.20.dist-info/top_level.txt
apicultur-0.1.20.dist-info/WHEEL
tests/test.py
tests/test_apicultur_io.py
tests/test_apicultur_store.py
tests/__init__.py
