Metadata-Version: 2.0
Name: apicultur
Version: 0.1.20
Summary: Python client to Apicultur API services
Home-page: https://github.com/jgsogo/apicultur-python
Author: Javier G. Sogo
Author-email: jgsogo@gmail.com
License: UNKNOWN
Keywords: api linguistic apicultur
Platform: UNKNOWN
Classifier: Development Status :: 4 - Beta
Classifier: Intended Audience :: Developers
Classifier: Topic :: Software Development :: Libraries
Classifier: Operating System :: OS Independent
Classifier: Programming Language :: Python
Classifier: Programming Language :: Python :: 2
Classifier: Programming Language :: Python :: 2.6
Classifier: Programming Language :: Python :: 2.7
Classifier: Programming Language :: Python :: 3
Classifier: Programming Language :: Python :: 3.2
Classifier: Programming Language :: Python :: 3.3
Classifier: Programming Language :: Python :: 3.4
Requires-Dist: requests
